{
  "$schema": "http://json.schemastore.org/sarif-1.0.0",
  "version": "1.0.0",
  "runs": [
    {
      "tool": {
        "name": "Compilador do Microsoft (R) Visual C#",
        "version": "3.7.0.0",
        "fileVersion": "3.7.0-6.20570.4 (dc3f4eef)",
        "semanticVersion": "3.7.0",
        "language": "pt-BR"
      },
      "results": [
        {
          "ruleId": "S3881",
          "level": "warning",
          "message": "Fix this implementation of 'IDisposable' to conform to the dispose pattern.",
          "locations": [
            {
              "resultFile": {
                "uri": "file:///C:/Users/MAPD-NOTE/source/repos/CondominioAppBackEnd2.0/src/Services/PreCadastro/CondominioAppPreCadastro.App/Aplication/Commands/LeadCommandHandler.cs",
                "region": {
                  "startLine": 16,
                  "startColumn": 18,
                  "endLine": 16,
                  "endColumn": 36
                }
              }
            }
          ],
          "relatedLocations": [
            {
              "physicalLocation": {
                "uri": "file:///C:/Users/MAPD-NOTE/source/repos/CondominioAppBackEnd2.0/src/Services/PreCadastro/CondominioAppPreCadastro.App/Aplication/Commands/LeadCommandHandler.cs",
                "region": {
                  "startLine": 16,
                  "startColumn": 18,
                  "endLine": 16,
                  "endColumn": 36
                }
              }
            },
            {
              "physicalLocation": {
                "uri": "file:///C:/Users/MAPD-NOTE/source/repos/CondominioAppBackEnd2.0/src/Services/PreCadastro/CondominioAppPreCadastro.App/Aplication/Commands/LeadCommandHandler.cs",
                "region": {
                  "startLine": 67,
                  "startColumn": 21,
                  "endLine": 67,
                  "endColumn": 28
                }
              }
            }
          ],
          "properties": {
            "warningLevel": 1,
            "customProperties": {
              "0": "Provide 'protected' overridable implementation of 'Dispose(bool)' on 'LeadCommandHandler' or mark the type as 'sealed'.",
              "1": "'LeadCommandHandler.Dispose()' should call 'Dispose(true)' and 'GC.SuppressFinalize(this)'."
            }
          }
        },
        {
          "ruleId": "S2933",
          "level": "warning",
          "message": "Make '_Assunto' 'readonly'.",
          "locations": [
            {
              "resultFile": {
                "uri": "file:///C:/Users/MAPD-NOTE/source/repos/CondominioAppBackEnd2.0/src/Services/PreCadastro/CondominioAppPreCadastro.App/EmailServices/EmailConfirmacaoDeCadastro.cs",
                "region": {
                  "startLine": 9,
                  "startColumn": 24,
                  "endLine": 9,
                  "endColumn": 32
                }
              }
            }
          ],
          "properties": {
            "warningLevel": 1
          }
        },
        {
          "ruleId": "S2933",
          "level": "warning",
          "message": "Make '_NomeDoUsuario' 'readonly'.",
          "locations": [
            {
              "resultFile": {
                "uri": "file:///C:/Users/MAPD-NOTE/source/repos/CondominioAppBackEnd2.0/src/Services/PreCadastro/CondominioAppPreCadastro.App/EmailServices/EmailConfirmacaoDeCadastro.cs",
                "region": {
                  "startLine": 10,
                  "startColumn": 24,
                  "endLine": 10,
                  "endColumn": 38
                }
              }
            }
          ],
          "properties": {
            "warningLevel": 1
          }
        },
        {
          "ruleId": "S2933",
          "level": "warning",
          "message": "Make '_EmailDoCliente' 'readonly'.",
          "locations": [
            {
              "resultFile": {
                "uri": "file:///C:/Users/MAPD-NOTE/source/repos/CondominioAppBackEnd2.0/src/Services/PreCadastro/CondominioAppPreCadastro.App/EmailServices/EmailConfirmacaoDeCadastro.cs",
                "region": {
                  "startLine": 11,
                  "startColumn": 24,
                  "endLine": 11,
                  "endColumn": 39
                }
              }
            }
          ],
          "properties": {
            "warningLevel": 1
          }
        },
        {
          "ruleId": "S3881",
          "level": "warning",
          "message": "Fix this implementation of 'IDisposable' to conform to the dispose pattern.",
          "locations": [
            {
              "resultFile": {
                "uri": "file:///C:/Users/MAPD-NOTE/source/repos/CondominioAppBackEnd2.0/src/Services/PreCadastro/CondominioAppPreCadastro.App/Data/Repository/LeadRepository.cs",
                "region": {
                  "startLine": 12,
                  "startColumn": 18,
                  "endLine": 12,
                  "endColumn": 32
                }
              }
            }
          ],
          "relatedLocations": [
            {
              "physicalLocation": {
                "uri": "file:///C:/Users/MAPD-NOTE/source/repos/CondominioAppBackEnd2.0/src/Services/PreCadastro/CondominioAppPreCadastro.App/Data/Repository/LeadRepository.cs",
                "region": {
                  "startLine": 12,
                  "startColumn": 18,
                  "endLine": 12,
                  "endColumn": 32
                }
              }
            },
            {
              "physicalLocation": {
                "uri": "file:///C:/Users/MAPD-NOTE/source/repos/CondominioAppBackEnd2.0/src/Services/PreCadastro/CondominioAppPreCadastro.App/Data/Repository/LeadRepository.cs",
                "region": {
                  "startLine": 75,
                  "startColumn": 21,
                  "endLine": 75,
                  "endColumn": 28
                }
              }
            }
          ],
          "properties": {
            "warningLevel": 1,
            "customProperties": {
              "0": "Provide 'protected' overridable implementation of 'Dispose(bool)' on 'LeadRepository' or mark the type as 'sealed'.",
              "1": "'LeadRepository.Dispose()' should call 'Dispose(true)' and 'GC.SuppressFinalize(this)'."
            }
          }
        },
        {
          "ruleId": "S2933",
          "level": "warning",
          "message": "Make '_Assunto' 'readonly'.",
          "locations": [
            {
              "resultFile": {
                "uri": "file:///C:/Users/MAPD-NOTE/source/repos/CondominioAppBackEnd2.0/src/Services/PreCadastro/CondominioAppPreCadastro.App/EmailServices/EmailPreCadastroEmpresa.cs",
                "region": {
                  "startLine": 11,
                  "startColumn": 24,
                  "endLine": 11,
                  "endColumn": 32
                }
              }
            }
          ],
          "properties": {
            "warningLevel": 1
          }
        },
        {
          "ruleId": "S2933",
          "level": "warning",
          "message": "Make '_lead' 'readonly'.",
          "locations": [
            {
              "resultFile": {
                "uri": "file:///C:/Users/MAPD-NOTE/source/repos/CondominioAppBackEnd2.0/src/Services/PreCadastro/CondominioAppPreCadastro.App/EmailServices/EmailPreCadastroEmpresa.cs",
                "region": {
                  "startLine": 12,
                  "startColumn": 22,
                  "endLine": 12,
                  "endColumn": 27
                }
              }
            }
          ],
          "properties": {
            "warningLevel": 1
          }
        },
        {
          "ruleId": "S3881",
          "level": "warning",
          "message": "Fix this implementation of 'IDisposable' to conform to the dispose pattern.",
          "locations": [
            {
              "resultFile": {
                "uri": "file:///C:/Users/MAPD-NOTE/source/repos/CondominioAppBackEnd2.0/src/Services/PreCadastro/CondominioAppPreCadastro.App/Aplication/Query/QueryLead.cs",
                "region": {
                  "startLine": 11,
                  "startColumn": 18,
                  "endLine": 11,
                  "endColumn": 27
                }
              }
            }
          ],
          "relatedLocations": [
            {
              "physicalLocation": {
                "uri": "file:///C:/Users/MAPD-NOTE/source/repos/CondominioAppBackEnd2.0/src/Services/PreCadastro/CondominioAppPreCadastro.App/Aplication/Query/QueryLead.cs",
                "region": {
                  "startLine": 11,
                  "startColumn": 18,
                  "endLine": 11,
                  "endColumn": 27
                }
              }
            },
            {
              "physicalLocation": {
                "uri": "file:///C:/Users/MAPD-NOTE/source/repos/CondominioAppBackEnd2.0/src/Services/PreCadastro/CondominioAppPreCadastro.App/Aplication/Query/QueryLead.cs",
                "region": {
                  "startLine": 52,
                  "startColumn": 21,
                  "endLine": 52,
                  "endColumn": 28
                }
              }
            }
          ],
          "properties": {
            "warningLevel": 1,
            "customProperties": {
              "0": "Provide 'protected' overridable implementation of 'Dispose(bool)' on 'QueryLead' or mark the type as 'sealed'.",
              "1": "'QueryLead.Dispose()' should call 'Dispose(true)' and 'GC.SuppressFinalize(this)'."
            }
          }
        },
        {
          "ruleId": "S2068",
          "level": "warning",
          "message": "Please review this hard-coded password.",
          "locations": [
            {
              "resultFile": {
                "uri": "file:///C:/Users/MAPD-NOTE/source/repos/CondominioAppBackEnd2.0/src/Services/PreCadastro/CondominioAppPreCadastro.App/EmailServices/SmtpSendBlue.cs",
                "region": {
                  "startLine": 11,
                  "startColumn": 27,
                  "endLine": 11,
                  "endColumn": 95
                }
              }
            }
          ],
          "properties": {
            "warningLevel": 1
          }
        },
        {
          "ruleId": "S2068",
          "level": "warning",
          "message": "Please review this hard-coded password.",
          "locations": [
            {
              "resultFile": {
                "uri": "file:///C:/Users/MAPD-NOTE/source/repos/CondominioAppBackEnd2.0/src/Services/PreCadastro/CondominioAppPreCadastro.App/EmailServices/SmtpAmazonService.cs",
                "region": {
                  "startLine": 11,
                  "startColumn": 27,
                  "endLine": 11,
                  "endColumn": 120
                }
              }
            }
          ],
          "properties": {
            "warningLevel": 1
          }
        },
        {
          "ruleId": "S3442",
          "level": "warning",
          "message": "Change the visibility of this constructor to 'protected'.",
          "locations": [
            {
              "resultFile": {
                "uri": "file:///C:/Users/MAPD-NOTE/source/repos/CondominioAppBackEnd2.0/src/Services/PreCadastro/CondominioAppPreCadastro.App/EmailServices/ServicoDeEmail.cs",
                "region": {
                  "startLine": 22,
                  "startColumn": 9,
                  "endLine": 22,
                  "endColumn": 15
                }
              }
            }
          ],
          "properties": {
            "warningLevel": 1
          }
        },
        {
          "ruleId": "S1905",
          "level": "warning",
          "message": "Remove this unnecessary cast to 'TipoDeDocumento'.",
          "locations": [
            {
              "resultFile": {
                "uri": "file:///C:/Users/MAPD-NOTE/source/repos/CondominioAppBackEnd2.0/src/Services/PreCadastro/CondominioAppPreCadastro.App/EmailServices/EmailPreCadastroEmpresa.cs",
                "region": {
                  "startLine": 66,
                  "startColumn": 137,
                  "endLine": 66,
                  "endColumn": 152
                }
              }
            }
          ],
          "properties": {
            "warningLevel": 1
          }
        },
        {
          "ruleId": "S1905",
          "level": "warning",
          "message": "Remove this unnecessary cast to 'TipoDeUnidade'.",
          "locations": [
            {
              "resultFile": {
                "uri": "file:///C:/Users/MAPD-NOTE/source/repos/CondominioAppBackEnd2.0/src/Services/PreCadastro/CondominioAppPreCadastro.App/EmailServices/EmailPreCadastroEmpresa.cs",
                "region": {
                  "startLine": 68,
                  "startColumn": 80,
                  "endLine": 68,
                  "endColumn": 93
                }
              }
            }
          ],
          "properties": {
            "warningLevel": 1
          }
        },
        {
          "ruleId": "S1905",
          "level": "warning",
          "message": "Remove this unnecessary cast to 'TipoDeGrupo'.",
          "locations": [
            {
              "resultFile": {
                "uri": "file:///C:/Users/MAPD-NOTE/source/repos/CondominioAppBackEnd2.0/src/Services/PreCadastro/CondominioAppPreCadastro.App/EmailServices/EmailPreCadastroEmpresa.cs",
                "region": {
                  "startLine": 72,
                  "startColumn": 78,
                  "endLine": 72,
                  "endColumn": 89
                }
              }
            }
          ],
          "properties": {
            "warningLevel": 1
          }
        },
        {
          "ruleId": "S1905",
          "level": "warning",
          "message": "Remove this unnecessary cast to 'TipoDePlano'.",
          "locations": [
            {
              "resultFile": {
                "uri": "file:///C:/Users/MAPD-NOTE/source/repos/CondominioAppBackEnd2.0/src/Services/PreCadastro/CondominioAppPreCadastro.App/EmailServices/EmailPreCadastroEmpresa.cs",
                "region": {
                  "startLine": 73,
                  "startColumn": 72,
                  "endLine": 73,
                  "endColumn": 83
                }
              }
            }
          ],
          "properties": {
            "warningLevel": 1
          }
        },
        {
          "ruleId": "S1643",
          "level": "warning",
          "message": "Use a StringBuilder instead.",
          "locations": [
            {
              "resultFile": {
                "uri": "file:///C:/Users/MAPD-NOTE/source/repos/CondominioAppBackEnd2.0/src/Services/PreCadastro/CondominioAppPreCadastro.App/ValueObjects/Telefone.cs",
                "region": {
                  "startLine": 56,
                  "startColumn": 21,
                  "endLine": 56,
                  "endColumn": 41
                }
              }
            }
          ],
          "properties": {
            "warningLevel": 1
          }
        },
        {
          "ruleId": "S1643",
          "level": "warning",
          "message": "Use a StringBuilder instead.",
          "locations": [
            {
              "resultFile": {
                "uri": "file:///C:/Users/MAPD-NOTE/source/repos/CondominioAppBackEnd2.0/src/Services/PreCadastro/CondominioAppPreCadastro.App/ValueObjects/Telefone.cs",
                "region": {
                  "startLine": 59,
                  "startColumn": 21,
                  "endLine": 59,
                  "endColumn": 40
                }
              }
            }
          ],
          "properties": {
            "warningLevel": 1
          }
        },
        {
          "ruleId": "S1643",
          "level": "warning",
          "message": "Use a StringBuilder instead.",
          "locations": [
            {
              "resultFile": {
                "uri": "file:///C:/Users/MAPD-NOTE/source/repos/CondominioAppBackEnd2.0/src/Services/PreCadastro/CondominioAppPreCadastro.App/ValueObjects/Telefone.cs",
                "region": {
                  "startLine": 61,
                  "startColumn": 17,
                  "endLine": 61,
                  "endColumn": 37
                }
              }
            }
          ],
          "properties": {
            "warningLevel": 1
          }
        },
        {
          "ruleId": "S1643",
          "level": "warning",
          "message": "Use a StringBuilder instead.",
          "locations": [
            {
              "resultFile": {
                "uri": "file:///C:/Users/MAPD-NOTE/source/repos/CondominioAppBackEnd2.0/src/Services/PreCadastro/CondominioAppPreCadastro.App/ValueObjects/Telefone.cs",
                "region": {
                  "startLine": 76,
                  "startColumn": 21,
                  "endLine": 76,
                  "endColumn": 41
                }
              }
            }
          ],
          "properties": {
            "warningLevel": 1
          }
        },
        {
          "ruleId": "S1643",
          "level": "warning",
          "message": "Use a StringBuilder instead.",
          "locations": [
            {
              "resultFile": {
                "uri": "file:///C:/Users/MAPD-NOTE/source/repos/CondominioAppBackEnd2.0/src/Services/PreCadastro/CondominioAppPreCadastro.App/ValueObjects/Telefone.cs",
                "region": {
                  "startLine": 79,
                  "startColumn": 21,
                  "endLine": 79,
                  "endColumn": 40
                }
              }
            }
          ],
          "properties": {
            "warningLevel": 1
          }
        },
        {
          "ruleId": "S1643",
          "level": "warning",
          "message": "Use a StringBuilder instead.",
          "locations": [
            {
              "resultFile": {
                "uri": "file:///C:/Users/MAPD-NOTE/source/repos/CondominioAppBackEnd2.0/src/Services/PreCadastro/CondominioAppPreCadastro.App/ValueObjects/Telefone.cs",
                "region": {
                  "startLine": 81,
                  "startColumn": 17,
                  "endLine": 81,
                  "endColumn": 37
                }
              }
            }
          ],
          "properties": {
            "warningLevel": 1
          }
        },
        {
          "ruleId": "S2971",
          "level": "warning",
          "message": "Drop this useless call to 'ToList' or replace it by 'AsEnumerable' if you are using LINQ to Entities.",
          "locations": [
            {
              "resultFile": {
                "uri": "file:///C:/Users/MAPD-NOTE/source/repos/CondominioAppBackEnd2.0/src/Services/PreCadastro/CondominioAppPreCadastro.App/ValueObjects/Foto.cs",
                "region": {
                  "startLine": 44,
                  "startColumn": 34,
                  "endLine": 44,
                  "endColumn": 40
                }
              }
            }
          ],
          "properties": {
            "warningLevel": 1
          }
        },
        {
          "ruleId": "S1643",
          "level": "warning",
          "message": "Use a StringBuilder instead.",
          "locations": [
            {
              "resultFile": {
                "uri": "file:///C:/Users/MAPD-NOTE/source/repos/CondominioAppBackEnd2.0/src/Services/PreCadastro/CondominioAppPreCadastro.App/ValueObjects/Endereco.cs",
                "region": {
                  "startLine": 33,
                  "startColumn": 25,
                  "endLine": 33,
                  "endColumn": 45
                }
              }
            }
          ],
          "properties": {
            "warningLevel": 1
          }
        },
        {
          "ruleId": "S1643",
          "level": "warning",
          "message": "Use a StringBuilder instead.",
          "locations": [
            {
              "resultFile": {
                "uri": "file:///C:/Users/MAPD-NOTE/source/repos/CondominioAppBackEnd2.0/src/Services/PreCadastro/CondominioAppPreCadastro.App/ValueObjects/Endereco.cs",
                "region": {
                  "startLine": 35,
                  "startColumn": 21,
                  "endLine": 35,
                  "endColumn": 44
                }
              }
            }
          ],
          "properties": {
            "warningLevel": 1
          }
        },
        {
          "ruleId": "S107",
          "level": "warning",
          "message": "Constructor has 17 parameters, which is greater than the 7 authorized.",
          "locations": [
            {
              "resultFile": {
                "uri": "file:///C:/Users/MAPD-NOTE/source/repos/CondominioAppBackEnd2.0/src/Services/PreCadastro/CondominioAppPreCadastro.App/Models/Condominio.cs",
                "region": {
                  "startLine": 57,
                  "startColumn": 26,
                  "endLine": 61,
                  "endColumn": 31
                }
              }
            }
          ],
          "properties": {
            "warningLevel": 1
          }
        },
        {
          "ruleId": "S1643",
          "level": "warning",
          "message": "Use a StringBuilder instead.",
          "locations": [
            {
              "resultFile": {
                "uri": "file:///C:/Users/MAPD-NOTE/source/repos/CondominioAppBackEnd2.0/src/Services/PreCadastro/CondominioAppPreCadastro.App/ValueObjects/Cpf.cs",
                "region": {
                  "startLine": 54,
                  "startColumn": 21,
                  "endLine": 54,
                  "endColumn": 38
                }
              }
            }
          ],
          "properties": {
            "warningLevel": 1
          }
        },
        {
          "ruleId": "S1643",
          "level": "warning",
          "message": "Use a StringBuilder instead.",
          "locations": [
            {
              "resultFile": {
                "uri": "file:///C:/Users/MAPD-NOTE/source/repos/CondominioAppBackEnd2.0/src/Services/PreCadastro/CondominioAppPreCadastro.App/ValueObjects/Cpf.cs",
                "region": {
                  "startLine": 59,
                  "startColumn": 29,
                  "endLine": 59,
                  "endColumn": 43
                }
              }
            }
          ],
          "properties": {
            "warningLevel": 1
          }
        },
        {
          "ruleId": "S1643",
          "level": "warning",
          "message": "Use a StringBuilder instead.",
          "locations": [
            {
              "resultFile": {
                "uri": "file:///C:/Users/MAPD-NOTE/source/repos/CondominioAppBackEnd2.0/src/Services/PreCadastro/CondominioAppPreCadastro.App/ValueObjects/Cpf.cs",
                "region": {
                  "startLine": 61,
                  "startColumn": 29,
                  "endLine": 61,
                  "endColumn": 43
                }
              }
            }
          ],
          "properties": {
            "warningLevel": 1
          }
        },
        {
          "ruleId": "S3249",
          "level": "warning",
          "message": "Remove this 'base' call to 'object.GetHashCode', which is directly based on the object reference.",
          "locations": [
            {
              "resultFile": {
                "uri": "file:///C:/Users/MAPD-NOTE/source/repos/CondominioAppBackEnd2.0/src/Services/PreCadastro/CondominioAppPreCadastro.App/ValueObjects/Email.cs",
                "region": {
                  "startLine": 42,
                  "startColumn": 20,
                  "endLine": 42,
                  "endColumn": 38
                }
              }
            }
          ],
          "properties": {
            "warningLevel": 1
          }
        }
      ],
      "rules": {
        "S107": {
          "id": "S107",
          "shortDescription": "Methods should not have too many parameters",
          "fullDescription": "A long parameter list can indicate that a new structure should be created to wrap the numerous parameters or that the function is doing too many things.",
          "defaultLevel": "warning",
          "helpUri": "https://rules.sonarsource.com/csharp/RSPEC-107",
          "properties": {
            "category": "Major Code Smell",
            "isEnabledByDefault": false,
            "tags": [
              "C#",
              "SonarWay",
              "MainSourceScope",
              "TestSourceScope"
            ]
          }
        },
        "S1643": {
          "id": "S1643",
          "shortDescription": "Strings should not be concatenated using '+' in a loop",
          "fullDescription": "StringBuilder is more efficient than string concatenation, especially when the operator is repeated over and over as in loops.",
          "defaultLevel": "warning",
          "helpUri": "https://rules.sonarsource.com/csharp/RSPEC-1643",
          "properties": {
            "category": "Minor Code Smell",
            "isEnabledByDefault": true,
            "tags": [
              "C#",
              "SonarWay",
              "MainSourceScope"
            ]
          }
        },
        "S1905": {
          "id": "S1905",
          "shortDescription": "Redundant casts should not be used",
          "fullDescription": "Unnecessary casting expressions make the code harder to read and understand.",
          "defaultLevel": "warning",
          "helpUri": "https://rules.sonarsource.com/csharp/RSPEC-1905",
          "properties": {
            "category": "Minor Code Smell",
            "isEnabledByDefault": true,
            "tags": [
              "C#",
              "SonarWay",
              "MainSourceScope",
              "TestSourceScope"
            ]
          }
        },
        "S2068": {
          "id": "S2068",
          "shortDescription": "Hard-coded credentials are security-sensitive",
          "fullDescription": "Because it is easy to extract strings from an application source code or binary, credentials should not be hard-coded. This is particularly true for applications that are distributed or that are open-source.",
          "defaultLevel": "warning",
          "helpUri": "https://rules.sonarsource.com/csharp/RSPEC-2068",
          "properties": {
            "category": "Blocker Security Hotspot",
            "isEnabledByDefault": true,
            "tags": [
              "C#",
              "SonarWay",
              "MainSourceScope",
              "NotConfigurable"
            ]
          }
        },
        "S2933": {
          "id": "S2933",
          "shortDescription": "Fields that are only assigned in the constructor should be \"readonly\"",
          "fullDescription": "readonly fields can only be assigned in a class constructor. If a class has a field that's not marked readonly but is only set in the constructor, it could cause confusion about the field's intended use. To avoid confusion, such fields should be marked readonly to make their intended use explicit, and to prevent future maintainers from inadvertently changing their use.",
          "defaultLevel": "warning",
          "helpUri": "https://rules.sonarsource.com/csharp/RSPEC-2933",
          "properties": {
            "category": "Major Code Smell",
            "isEnabledByDefault": true,
            "tags": [
              "C#",
              "SonarWay",
              "MainSourceScope",
              "TestSourceScope"
            ]
          }
        },
        "S2971": {
          "id": "S2971",
          "shortDescription": "\"IEnumerable\" LINQs should be simplified",
          "fullDescription": "In the interests of readability, code that can be simplified should be simplified. To that end, there are several ways IEnumerable language integrated queries (LINQ) can be simplified",
          "defaultLevel": "warning",
          "helpUri": "https://rules.sonarsource.com/csharp/RSPEC-2971",
          "properties": {
            "category": "Major Code Smell",
            "isEnabledByDefault": true,
            "tags": [
              "C#",
              "SonarWay",
              "MainSourceScope",
              "TestSourceScope"
            ]
          }
        },
        "S3249": {
          "id": "S3249",
          "shortDescription": "Classes directly extending \"object\" should not call \"base\" in \"GetHashCode\" or \"Equals\"",
          "fullDescription": "Making a base call in an overriding method is generally a good idea, but not in GetHashCode and Equals for classes that directly extend object because those methods are based on the object reference. Meaning that no two objects that use those base methods will ever be equal or have the same hash.",
          "defaultLevel": "warning",
          "helpUri": "https://rules.sonarsource.com/csharp/RSPEC-3249",
          "properties": {
            "category": "Major Bug",
            "isEnabledByDefault": true,
            "tags": [
              "C#",
              "SonarWay",
              "MainSourceScope",
              "TestSourceScope"
            ]
          }
        },
        "S3442": {
          "id": "S3442",
          "shortDescription": "\"abstract\" classes should not have \"public\" constructors",
          "fullDescription": "Since abstract classes can't be instantiated, there's no point in their having public or internal constructors. If there is basic initialization logic that should run when an extending class instance is created, you can by all means put it in a constructor, but make that constructor private or protected.",
          "defaultLevel": "warning",
          "helpUri": "https://rules.sonarsource.com/csharp/RSPEC-3442",
          "properties": {
            "category": "Major Code Smell",
            "isEnabledByDefault": true,
            "tags": [
              "C#",
              "SonarWay",
              "MainSourceScope",
              "TestSourceScope"
            ]
          }
        },
        "S3881": {
          "id": "S3881",
          "shortDescription": "\"IDisposable\" should be implemented correctly",
          "fullDescription": "The IDisposable interface is a mechanism to release unmanaged resources, if not implemented correctly this could result in resource leaks or more severe bugs.",
          "defaultLevel": "warning",
          "helpUri": "https://rules.sonarsource.com/csharp/RSPEC-3881",
          "properties": {
            "category": "Major Code Smell",
            "isEnabledByDefault": true,
            "tags": [
              "C#",
              "SonarWay",
              "MainSourceScope",
              "TestSourceScope"
            ]
          }
        }
      }
    }
  ]
}